geoevo/__init__.py
geoevo/adj_soc.csv
geoevo/example.py
geoevo/geoevo.py
geoevo/train_soc.csv
geoevo-0.0.3.dist-info/METADATA
geoevo-0.0.3.dist-info/WHEEL
geoevo-0.0.3.dist-info/licenses/LICENSE
geoevo-0.0.3.dist-info/RECORD
