Metadata-Version: 2.4
Name: geoevo
Version: 0.0.3
Summary: GeoEvo
Project-URL: Homepage, https://github.com/WenHZhang/geoevo
Project-URL: Issues, https://github.com/WenHZhang/geoevo/issues
Author-email: Wenhui Zhang <zhangwenhui242@mails.ucas.ac.cn>
License-Expression: MIT
License-File: LICENSE
Classifier: Operating System :: OS Independent
Classifier: Programming Language :: Python :: 3
Requires-Python: >=3.0
